Workbook

Sheet Projections
A1: دمشق ترانزيت — النموذج المالي | Damascus Transit — Financial Model
A2: USD model (contract currency). New-SYP shown at FX below (post-Jan-2026 redenomination; ~June 2026; indicative). Blue = input you can change; black = formula.
A4: البند / Item | B4: وحدة/Unit | C4: May'26 | D4: Jun'26 | E4: Jul'26 | F4: Aug'26 | G4: Sep'26 | H4: Oct'26 | I4: Nov'26 | J4: Dec'26 | K4: Jan'27 | L4: Feb'27 | M4: Mar'27 | N4: Apr'27 | O4: السنة 1 / Yr 1
A5: سعر الصرف (ل.س جديدة/دولار) / FX (new SYP per USD) | C5: 115.5
A6: المُدخلات / INPUTS
A7: المركبات المتعاقدة / Vehicles under contract | B7: # | C7: 50 | D7: 50 | E7: 50 | F7: 50 | G7: 50 | H7: 50 | I7: 150 | J7: 200 | K7: 300 | L7: 380 | M7: 450 | N7: 500 | O7: =N7 -> 500
A8: رسم المنصّة الحكومي / Government platform fee | B8: $/mo | C8: 500 | D8: 500 | E8: 500 | F8: 500 | G8: 500 | H8: 500 | I8: 5000 | J8: 5000 | K8: 5000 | L8: 5000 | M8: 5000 | N8: 5000 | O8: =SUM(C8:N8) -> 33000
A9: عدد المشغّلين (SaaS) / Operators on SaaS | B9: # | C9: 0 | D9: 0 | E9: 0 | F9: 0 | G9: 0 | H9: 0 | I9: 3 | J9: 4 | K9: 6 | L9: 8 | M9: 10 | N9: 12 | O9: =SUM(C9:N9) -> 43
A10: سعر اشتراك المشغّل / SaaS price per operator | C10: 150
A11: ترخيص البيانات / Data licensing | B11: $/mo | C11: 0 | D11: 0 | E11: 0 | F11: 0 | G11: 0 | H11: 0 | I11: 0 | J11: 0 | K11: 0 | L11: 0 | M11: 1000 | N11: 2000 | O11: =SUM(C11:N11) -> 3000
A12: كلفة متغيّرة لكل مركبة / Variable cost per vehicle | C12: 2
A13: البنية السحابية / Cloud infrastructure | B13: $/mo | C13: 0 | D13: 0 | E13: 0 | F13: 0 | G13: 0 | H13: 0 | I13: 50 | J13: 50 | K13: 50 | L13: 150 | M13: 150 | N13: 150 | O13: =SUM(C13:N13) -> 600
A14: مكتب وتشغيل / Office & operations | B14: $/mo | C14: 0 | D14: 0 | E14: 0 | F14: 0 | G14: 0 | H14: 0 | I14: 500 | J14: 500 | K14: 500 | L14: 500 | M14: 500 | N14: 500 | O14: =SUM(C14:N14) -> 3000
A15: عتاد GPS (لمرة واحدة) / GPS hardware (one-time) | B15: $ | C15: 0 | D15: 7150 | E15: 0 | F15: 0 | G15: 0 | H15: 0 | I15: 0 | J15: 0 | K15: 0 | L15: 0 | M15: 0 | N15: 0 | O15: =SUM(C15:N15) -> 7150
A16: الإيرادات / REVENUE
A17: عقد حكومي / Government contract | B17: $/mo | C17: =C8 -> 500 | D17: =D8 -> 500 | E17: =E8 -> 500 | F17: =F8 -> 500 | G17: =G8 -> 500 | H17: =H8 -> 500 | I17: =I8 -> 5000 | J17: =J8 -> 5000 | ... N17: =N8 -> 5000 | O17: =SUM(C17:N17) -> 33000
A18: اشتراكات المشغّلين / Operator SaaS | B18: $/mo | C18: =C9*$C$10 -> 0 | D18: =D9*$C$10 -> 0 | E18: =E9*$C$10 -> 0 | F18: =F9*$C$10 -> 0 | G18: =G9*$C$10 -> 0 | H18: =H9*$C$10 -> 0 | I18: =I9*$C$10 -> 450 | J18: =J9*$C$10 -> 600 | ... N18: =N9*$C$10 -> 1800 | O18: =SUM(C18:N18) -> 6450
A19: ترخيص البيانات / Data licensing | B19: $/mo | C19: =C11 -> 0 | D19: =D11 -> 0 | E19: =E11 -> 0 | F19: =F11 -> 0 | G19: =G11 -> 0 | H19: =H11 -> 0 | I19: =I11 -> 0 | J19: =J11 -> 0 | ... N19: =N11 -> 2000 | O19: =SUM(C19:N19) -> 3000
A20: إجمالي الإيراد الشهري / Total monthly revenue | B20: $/mo | C20: =C17+C18+C19 -> 500 | D20: =D17+D18+D19 -> 500 | E20: =E17+E18+E19 -> 500 | F20: =F17+F18+F19 -> 500 | G20: =G17+G18+G19 -> 500 | H20: =H17+H18+H19 -> 500 | I20: =I17+I18+I19 -> 5450 | J20: =J17+J18+J19 -> 5600 | ... N20: =N17+N18+N19 -> 8800 | O20: =SUM(C20:N20) -> 42450
A21: الإيراد التراكمي / Cumulative revenue | B21: $ | C21: =C20 -> 500 | D21: =C21+D20 -> 1000 | E21: =D21+E20 -> 1500 | F21: =E21+F20 -> 2000 | G21: =F21+G20 -> 2500 | H21: =G21+H20 -> 3000 | I21: =H21+I20 -> 8450 | J21: =I21+J20 -> 14050 | K21: =J21+K20 -> 19950 | ... N21: =M21+N20 -> 42450 | O21: =N21 -> 42450
A22: التكاليف / COSTS
A23: كلفة متغيّرة / Variable cost | B23: $/mo | C23: =C7*$C$12 -> 100 | D23: =D7*$C$12 -> 100 | E23: =E7*$C$12 -> 100 | F23: =F7*$C$12 -> 100 | G23: =G7*$C$12 -> 100 | H23: =H7*$C$12 -> 100 | I23: =I7*$C$12 -> 300 | J23: =J7*$C$12 -> 400 | ... N23: =N7*$C$12 -> 1000 | O23: =SUM(C23:N23) -> 4560
A24: بنية سحابية / Infrastructure | B24: $/mo | C24: =C13 -> 0 | D24: =D13 -> 0 | E24: =E13 -> 0 | F24: =F13 -> 0 | G24: =G13 -> 0 | H24: =H13 -> 0 | I24: =I13 -> 50 | J24: =J13 -> 50 | ... N24: =N13 -> 150 | O24: =SUM(C24:N24) -> 600
A25: مكتب وتشغيل / Office & ops | B25: $/mo | C25: =C14 -> 0 | D25: =D14 -> 0 | E25: =E14 -> 0 | F25: =F14 -> 0 | G25: =G14 -> 0 | H25: =H14 -> 0 | I25: =I14 -> 500 | J25: =J14 -> 500 | ... N25: =N14 -> 500 | O25: =SUM(C25:N25) -> 3000
A26: عتاد (لمرة واحدة) / Hardware (one-time) | B26: $ | C26: =C15 -> 0 | D26: =D15 -> 7150 | E26: =E15 -> 0 | F26: =F15 -> 0 | G26: =G15 -> 0 | H26: =H15 -> 0 | I26: =I15 -> 0 | J26: =J15 -> 0 | ... N26: =N15 -> 0 | O26: =SUM(C26:N26) -> 7150
A27: إجمالي التكلفة الشهرية / Total monthly cost | B27: $/mo | C27: =C23+C24+C25+C26 -> 100 | D27: =D23+D24+D25+D26 -> 7250 | E27: =E23+E24+E25+E26 -> 100 | F27: =F23+F24+F25+F26 -> 100 | G27: =G23+G24+G25+G26 -> 100 | H27: =H23+H24+H25+H26 -> 100 | I27: =I23+I24+I25+I26 -> 850 | J27: =J23+J24+J25+J26 -> 950 | ... N27: =N23+N24+N25+N26 -> 1650 | O27: =SUM(C27:N27) -> 15310
A28: الربح / PROFIT
A29: الربح الإجمالي / Gross profit (rev−var−infra) | B29: $/mo | C29: =C20-C23-C24 -> 400 | D29: =D20-D23-D24 -> 400 | E29: =E20-E23-E24 -> 400 | F29: =F20-F23-F24 -> 400 | G29: =G20-G23-G24 -> 400 | H29: =H20-H23-H24 -> 400 | I29: =I20-I23-I24 -> 5100 | J29: =J20-J23-J24 -> 5150 | ... N29: =N20-N23-N24 -> 7650 | O29: =SUM(C29:N29) -> 37290
A30: هامش الربح الإجمالي / Gross margin | B30: % | C30: =IF(C20=0,0,C29/C20) -> 0.8 | D30: =IF(D20=0,0,D29/D20) -> 0.8 | E30: =IF(E20=0,0,E29/E20) -> 0.8 | F30: =IF(F20=0,0,F29/F20) -> 0.8 | G30: =IF(G20=0,0,G29/G20) -> 0.8 | H30: =IF(H20=0,0,H29/H20) -> 0.8 | I30: =IF(I20=0,0,I29/I20) -> 0.93577982 | J30: =IF(J20=0,0,J29/J20) -> 0.91964286 | ... N30: =IF(N20=0,0,N29/N20) -> 0.86931818 | O30: =N30 -> 0.86931818
A31: الربح التشغيلي / Operating profit (rev−total cost) | B31: $/mo | C31: =C20-C27 -> 400 | D31: =D20-D27 -> -6750 | E31: =E20-E27 -> 400 | F31: =F20-F27 -> 400 | G31: =G20-G27 -> 400 | H31: =H20-H27 -> 400 | I31: =I20-I27 -> 4600 | J31: =J20-J27 -> 4650 | ... N31: =N20-N27 -> 7150 | O31: =SUM(C31:N31) -> 27140
A32: الربح التشغيلي التراكمي / Cumulative operating profit | B32: $ | C32: =C31 -> 400 | D32: =C32+D31 -> -6350 | E32: =D32+E31 -> -5950 | F32: =E32+F31 -> -5550 | G32: =F32+G31 -> -5150 | H32: =G32+H31 -> -4750 | I32: =H32+I31 -> -150 | J32: =I32+J31 -> 4500 | K32: =J32+K31 -> 9250 | ... N32: =M32+N31 -> 27140 | O32: =N32 -> 27140

Sheet Summary & Scenarios
A1: ملخّص مالي والسيناريوهات | Financial Summary & Scenarios
A2: Figures link to the Projections sheet. USD primary; SYP indicative at the FX on Projections.
A4: بند / Metric | B4: USD | C4: SYP | D4: ملاحظة / Note
A5: إيراد السنة الأولى / Year-1 revenue | B5: =Projections!O20 -> 42450 | C5: =B5*Projections!$C$5 -> 4902975 | D5: Base scenario
A6: تكلفة السنة الأولى / Year-1 cost | B6: =Projections!O27 -> 15310 | C6: =B6*Projections!$C$5 -> 1768305
A7: الربح التشغيلي السنة 1 / Year-1 operating profit | B7: =Projections!O31 -> 27140 | C7: =B7*Projections!$C$5 -> 3134670 | D7: ≈ after one-time hardware
A8: هامش الربح الإجمالي (الشهر 12) / Gross margin (M12) | B8: =Projections!N30 -> 0.86931818
A9: إيراد متكرّر شهري (الشهر 12) / MRR (Month 12) | B9: =Projections!N20 -> 8800 | C9: =B9*Projections!$C$5 -> 1016400
A10: المركبات (الشهر 12) / Vehicles (Month 12) | B10: =Projections!N7 -> 500
A12: سيناريو 12 شهراً / 12-Month Scenario | B12: الإيراد USD | C12: ≈ SYP | D12: الوصف / Description
A13: متحفّظ — تجربة فقط / Conservative — pilot only | B13: 3000 | C13: =B13*Projections!$C$5 -> 346500 | D13: 50 vehicles × $500 × 6 months
A14: أساسي — تجربة + المرحلة 2 / Base — pilot + Phase 2 | B14: =B6 -> 15310 | C14: =C6 -> 1768305 | D14: Year-1 model (this workbook)
A15: متفائل / Optimistic | B15: 200000 | C15: =B15*Projections!$C$5 -> 23100000 | D15: + grant funding + faster Phase 2 + operators
A17: نظرة السنة 2 / Year-2 Outlook | B17: القيمة | C17: ≈ SYP | D17: المصدر / Basis
A18: المركبات (الشهر 24) / Vehicles (Month 24) | B18: 2000 | D18: Damascus full + Aleppo entry
A19: الإيراد السنوي (الشهر 24) / ARR (Month 24) | B19: 630000 | C19: =B19*Projections!$C$5 -> 72765000 | D19: Gov + operator SaaS + data licensing
A21: اقتصاديات الوحدة / Unit Economics | B21: القيمة
A22: الإيراد لكل مركبة شهرياً / Revenue per vehicle | B22: $10–$50
A23: الكلفة لكل مركبة شهرياً / Cost per vehicle | B23: ≈ $2
A24: هامش إجمالي / Gross margin | B24: 80–96%
A25: نقطة التعادل / Break-even | B25: ~50 vehicles
A26: استرداد كلفة العتاد / Hardware payback | B26: 2–3 months
